creator/__init__.py
creator/auto/__init__.py
creator/auto/creator_auto.py
creator/auto/request_auto.py
creator/auto/response_auto.py
creator/base/__init__.py
creator/base/base_app.py
creator/base/base_request.py
creator/base/base_response.py
creator/base/job_status.py
creator/cmfy/__init__.py
creator/cmfy/creator_cmfy.py
creator/cmfy/request_cmfy.py
creator/cmfy/response_cmfy.py
creator/fcus_api/__init__.py
creator/fcus_api/creator_fcus_api.py
creator/fcus_api/request_fcus_api.py
creator/fcus_api/response_fcus_api.py
creator/util/__init__.py
creator/util/helper.py
gen_wrappers-0.7.1.dist-info/METADATA
gen_wrappers-0.7.1.dist-info/WHEEL
gen_wrappers-0.7.1.dist-info/top_level.txt
gen_wrappers-0.7.1.dist-info/RECORD
